ipyfs/__init__.py
ipyfs/ipfs.py
ipyfs/RPCs/__init__.py
ipyfs/RPCs/add.py
ipyfs/RPCs/bitswap.py
ipyfs/RPCs/block.py
ipyfs/RPCs/bootstrap.py
ipyfs/RPCs/cat.py
ipyfs/RPCs/cid.py
ipyfs/RPCs/commands.py
ipyfs/RPCs/config.py
ipyfs/RPCs/dag.py
ipyfs/RPCs/dht.py
ipyfs/RPCs/diag.py
ipyfs/RPCs/files.py
ipyfs/RPCs/filestore.py
ipyfs/RPCs/get.py
ipyfs/RPCs/id.py
ipyfs/RPCs/key.py
ipyfs/RPCs/log.py
ipyfs/RPCs/ls.py
ipyfs/RPCs/multibase.py
ipyfs/RPCs/name.py
ipyfs/RPCs/pin.py
ipyfs/RPCs/ping.py
ipyfs/RPCs/refs.py
ipyfs/RPCs/repo.py
ipyfs/RPCs/resolve.py
ipyfs/RPCs/shutdown.py
ipyfs/RPCs/stats.py
ipyfs/RPCs/swarm.py
ipyfs/RPCs/update.py
ipyfs/RPCs/version.py
ipyfs-0.1.3.dist-info/LICENSE
ipyfs-0.1.3.dist-info/METADATA
ipyfs-0.1.3.dist-info/WHEEL
ipyfs-0.1.3.dist-info/top_level.txt
ipyfs-0.1.3.dist-info/RECORD
