Metadata-Version: 2.1
Name: ipyfs
Version: 0.1.3
Summary: IPyFS, Python-based IPFS CLI.
Home-page: https://github.com/837477/IPyFS
Author: 837477
Author-email: 8374770@gmail.com
License: MIT
Keywords: ipyfs,ipfs,ipfs python,ipfs-python,iptf_python,python-ipfs,python_ipfs
Platform: any
Classifier: Intended Audience :: Developers
Classifier: License :: OSI Approved :: MIT License
Classifier: Operating System :: OS Independent
Classifier: Programming Language :: Python :: 3.7
Classifier: Programming Language :: Python :: 3.8
Classifier: Programming Language :: Python :: 3.9
Classifier: Programming Language :: Python :: 3.10
Classifier: Topic :: Internet :: WWW/HTTP :: Dynamic Content
Classifier: Topic :: Software Development :: Libraries :: Python Modules
License-File: LICENSE
Requires-Dist: requests
